permaviss/__init__.py
permaviss/version.py
permaviss/covers/__init__.py
permaviss/covers/cubical_cover.py
permaviss/gauss_mod_p/__init__.py
permaviss/gauss_mod_p/arithmetic_mod_p.py
permaviss/gauss_mod_p/functions.py
permaviss/gauss_mod_p/gauss_mod_p.py
permaviss/persistence_algebra/PH_classic.py
permaviss/persistence_algebra/__init__.py
permaviss/persistence_algebra/barcode_bases.py
permaviss/persistence_algebra/image_kernel.py
permaviss/persistence_algebra/module_persistence_homology.py
permaviss/sample_point_clouds/__init__.py
permaviss/sample_point_clouds/examples.py
permaviss/simplicial_complexes/__init__.py
permaviss/simplicial_complexes/differentials.py
permaviss/simplicial_complexes/flag_complex.py
permaviss/simplicial_complexes/vietoris_rips.py
permaviss/spectral_sequence/MV_spectral_seq.py
permaviss/spectral_sequence/__init__.py
permaviss/spectral_sequence/spectral_sequence_class.py
permaviss-0.0.2.dist-info/LICENSE.txt
permaviss-0.0.2.dist-info/METADATA
permaviss-0.0.2.dist-info/WHEEL
permaviss-0.0.2.dist-info/top_level.txt
permaviss-0.0.2.dist-info/RECORD
