Metadata-Version: 2.1
Name: permaviss
Version: 0.0.2
Summary: Persistence Mayer Vietoris spectral sequence
Home-page: https://github.com/atorras1618/PerMaViss
Author: Alvaro Torras Casas
Author-email: atorras1618@gmail.com
License: MIT
Download-URL: https://github.com/atorras1618/PerMaViss/tarball/v0.0.2
Keywords: spectral sequence,persistent homology,Mayer Vietoris
Platform: UNKNOWN
Requires-Python: >=3.6
